museflow/__init__.py
museflow/main.py
museflow/model_utils.py
museflow/note_sequence_utils.py
museflow/trainer.py
museflow/version.py
museflow/vocabulary.py
museflow/components/__init__.py
museflow/components/component.py
museflow/components/embedding_layer.py
museflow/components/rnn_decoder.py
museflow/components/rnn_layer.py
museflow/encodings/__init__.py
museflow/encodings/performance_encoding.py
museflow/encodings/piano_roll_encoding.py
museflow/io/__init__.py
museflow/io/note_sequence_io.py
museflow/models/__init__.py
museflow/models/rnn_generator.py
museflow/models/rnn_seq2seq.py
museflow/nn/__init__.py
museflow/nn/rnn.py
museflow/scripts/__init__.py
museflow/scripts/chop_midi.py
museflow/scripts/mix_midi.py
museflow/scripts/notes2midi.py
museflow/tests/__init__.py
museflow/tests/test_model_utils.py
museflow/tests/test_performance_encoding.py
museflow-1.0.0.dist-info/LICENSE
museflow-1.0.0.dist-info/METADATA
museflow-1.0.0.dist-info/WHEEL
museflow-1.0.0.dist-info/entry_points.txt
museflow-1.0.0.dist-info/top_level.txt
museflow-1.0.0.dist-info/RECORD
