Metadata-Version: 2.1
Name: museflow
Version: 1.0.0
Summary: Music sequence learning toolkit
Home-page: https://github.com/cifkao/museflow
Author: Ondřej Cífka
Author-email: ondra@cifka.com
License: UNKNOWN
Platform: UNKNOWN
Classifier: Programming Language :: Python :: 3
Classifier: Programming Language :: Python :: 3 :: Only
Classifier: Programming Language :: Python :: 3.6
Classifier: Programming Language :: Python :: 3.7
Classifier: Programming Language :: Python :: 3.8
Classifier: Programming Language :: Python :: 3.9
Classifier: Operating System :: OS Independent
Classifier: License :: OSI Approved :: BSD License
Classifier: Topic :: Software Development :: Libraries :: Python Modules
Classifier: Topic :: Utilities
Classifier: Intended Audience :: Developers
Classifier: Intended Audience :: Science/Research
Requires-Python: >=3.6
Requires-Dist: cached-property
Requires-Dist: coloredlogs
Requires-Dist: confugue
Requires-Dist: lmdb
Requires-Dist: numpy
Requires-Dist: pretty-midi
Requires-Dist: pyyaml
Requires-Dist: note-seq
Provides-Extra: gpu
Requires-Dist: tensorflow-gpu (<2.0) ; extra == 'gpu'
Provides-Extra: nogpu
Requires-Dist: tensorflow (<2.0) ; extra == 'nogpu'
